tlv.cp312-win_amd64.pyd
pyiqcsdk/__init__.py
pyiqcsdk/api.py
pyiqcsdk/cianames.py
pyiqcsdk/parts.py
pyiqcsdk/scenario.py
pyiqcsdk/subscriber.py
pyiqcsdk/utils.py
pyiqcsdk/version.py
pyiqcsdk/lib/include/addrchk.h
pyiqcsdk/lib/include/bitalgs.h
pyiqcsdk/lib/include/cexcept.h
pyiqcsdk/lib/include/cipaddr.h
pyiqcsdk/lib/include/cmacaddr.h
pyiqcsdk/lib/include/cpointer.h
pyiqcsdk/lib/include/eendian.h
pyiqcsdk/lib/include/tlv_def.h
pyiqcsdk/lib/include/tlvpacket.h
pyiqcsdk-2.1.1.dist-info/licenses/LICENSE
pyiqcsdk-2.1.1.dist-info/METADATA
pyiqcsdk-2.1.1.dist-info/WHEEL
pyiqcsdk-2.1.1.dist-info/top_level.txt
pyiqcsdk-2.1.1.dist-info/RECORD
