Metadata-Version: 2.4
Name: pyiqcsdk
Version: 2.1.1
Summary: A Python SDK library for ExtremeCloud IQ Controller
Home-page: https://github.com/extremenetworks/pyxccsdk
Author: Extreme Networks
Author-email: pylist@extremenetworks.com
Project-URL: Documentation, https://github.com/extremenetworks/pyxccsdk
Classifier: Development Status :: 4 - Beta
Classifier: Environment :: Other Environment
Classifier: Intended Audience :: Developers
Classifier: Operating System :: OS Independent
Classifier: Programming Language :: Python :: 3 :: Only
Classifier: Topic :: Software Development
Classifier: Topic :: Utilities
Classifier: License :: OSI Approved :: MIT License
Requires-Python: >=3.5
License-File: LICENSE
Requires-Dist: requests
Dynamic: author
Dynamic: author-email
Dynamic: classifier
Dynamic: description
Dynamic: description-content-type
Dynamic: home-page
Dynamic: license-file
Dynamic: project-url
Dynamic: requires-dist
Dynamic: requires-python
Dynamic: summary
